spectre_core/__init__.py
spectre_core/exceptions.py
spectre_core/py.typed
spectre_core/batches/__init__.py
spectre_core/batches/_base.py
spectre_core/batches/_batches.py
spectre_core/batches/_callisto.py
spectre_core/batches/_iq_stream.py
spectre_core/config/__init__.py
spectre_core/config/_paths.py
spectre_core/config/_time_formats.py
spectre_core/events/__init__.py
spectre_core/events/_base.py
spectre_core/events/_fixed_center_frequency.py
spectre_core/events/_stfft.py
spectre_core/events/_swept_center_frequency.py
spectre_core/fields/__init__.py
spectre_core/fields/_fields.py
spectre_core/flowgraphs/__init__.py
spectre_core/flowgraphs/_base.py
spectre_core/flowgraphs/_hackrf.py
spectre_core/flowgraphs/_rsp1a.py
spectre_core/flowgraphs/_rspduo.py
spectre_core/flowgraphs/_rspdx.py
spectre_core/flowgraphs/_rtlsdr.py
spectre_core/flowgraphs/_signal_generator.py
spectre_core/flowgraphs/_usrp.py
spectre_core/io/__init__.py
spectre_core/io/_files.py
spectre_core/jobs/__init__.py
spectre_core/jobs/_duration.py
spectre_core/jobs/_jobs.py
spectre_core/jobs/_workers.py
spectre_core/logs/__init__.py
spectre_core/logs/_configure.py
spectre_core/logs/_decorators.py
spectre_core/logs/_logs.py
spectre_core/logs/_process_types.py
spectre_core/models/__init__.py
spectre_core/models/_b200mini.py
spectre_core/models/_hackrf.py
spectre_core/models/_hackrfone.py
spectre_core/models/_rsp1a.py
spectre_core/models/_rspduo.py
spectre_core/models/_rspdx.py
spectre_core/models/_rtlsdr.py
spectre_core/models/_sdrplay_validators.py
spectre_core/models/_signal_generator.py
spectre_core/models/_usrp.py
spectre_core/models/_usrp_validators.py
spectre_core/models/_validators.py
spectre_core/plotting/__init__.py
spectre_core/plotting/_base.py
spectre_core/plotting/_format.py
spectre_core/plotting/_panel_names.py
spectre_core/plotting/_panel_stack.py
spectre_core/plotting/_panels.py
spectre_core/receivers/__init__.py
spectre_core/receivers/_b200mini.py
spectre_core/receivers/_base.py
spectre_core-2.0.0.dist-info/licenses/LICENSE
spectre_core-2.0.0.dist-info/METADATA
spectre_core-2.0.0.dist-info/WHEEL
spectre_core-2.0.0.dist-info/top_level.txt
spectre_core-2.0.0.dist-info/RECORD
