Metadata-Version: 2.4
Name: spectre-core
Version: 2.0.0
Summary: The core Python package used by the spectre program. 
Maintainer-email: Jimmy Fitzpatrick <jcfitzpatrick12@gmail.com>
License:                     GNU GENERAL PUBLIC LICENSE
Project-URL: Homepage, https://github.com/jcfitzpatrick12/spectre-core
Project-URL: Issues, https://github.com/jcfitzpatrick12/spectre-core/issues
Classifier: Programming Language :: Python :: 3
Classifier: License :: OSI Approved :: GNU General Public License v3 (GPLv3)
Classifier: Operating System :: POSIX :: Linux
Requires-Python: >=3.10.2
License-File: LICENSE
Requires-Dist: numpy==1.24.0
Requires-Dist: pyfftw==0.15.0
Requires-Dist: astropy==6.0.1
Requires-Dist: pydantic==2.12.3
Requires-Dist: matplotlib==3.5.0
Requires-Dist: watchdog==4.0.0
Provides-Extra: test
Requires-Dist: pytest; extra == "test"
Requires-Dist: mypy; extra == "test"
Requires-Dist: black; extra == "test"
Dynamic: license-file
